{
  "_format": "hh-sol-cache-2",
  "files": {
    "/home/swatimalode/Documents/Alloy/audit/smartcontract/node_modules/@openzeppelin/contracts-upgradeable/utils/ContextUpgradeable.sol": {
      "lastModificationDate": 1684824406466,
      "contentHash": "6200b84950eb05b4a92a39fd1d6e0f9b",
      "sourceName": "@openzeppelin/contracts-upgradeable/utils/ContextUpgradeable.sol",
      "solcConfig": {
        "version": "0.8.16",
        "settings": {
          "optimizer": {
            "enabled": false,
            "runs": 200
          },
          "outputSelection": {
            "*": {
              "*": [
                "abi",
                "evm.bytecode",
                "evm.deployedBytecode",
                "evm.methodIdentifiers",
                "metadata",
                "storageLayout"
              ],
              "": [
                "ast"
              ]
            }
          },
          "metadata": {
            "useLiteralContent": false
          }
        }
      },
      "imports": [
        "../proxy/utils/Initializable.sol"
      ],
      "versionPragmas": [
        "^0.8.0"
      ],
      "artifacts": [
        "ContextUpgradeable"
      ]
    },
    "/home/swatimalode/Documents/Alloy/audit/smartcontract/node_modules/@openzeppelin/contracts-upgradeable/token/ERC20/IERC20Upgradeable.sol": {
      "lastModificationDate": 1684824407326,
      "contentHash": "a9ed3c7bc7d9ebb5e34f20829274f088",
      "sourceName": "@openzeppelin/contracts-upgradeable/token/ERC20/IERC20Upgradeable.sol",
      "solcConfig": {
        "version": "0.8.16",
        "settings": {
          "optimizer": {
            "enabled": false,
            "runs": 200
          },
          "outputSelection": {
            "*": {
              "*": [
                "abi",
                "evm.bytecode",
                "evm.deployedBytecode",
                "evm.methodIdentifiers",
                "metadata",
                "storageLayout"
              ],
              "": [
                "ast"
              ]
            }
          },
          "metadata": {
            "useLiteralContent": false
          }
        }
      },
      "imports": [],
      "versionPragmas": [
        "^0.8.0"
      ],
      "artifacts": [
        "IERC20Upgradeable"
      ]
    },
    "/home/swatimalode/Documents/Alloy/audit/smartcontract/node_modules/@openzeppelin/contracts-upgradeable/proxy/utils/Initializable.sol": {
      "lastModificationDate": 1684824407578,
      "contentHash": "fc5844e59776a976987884e4d9814c7d",
      "sourceName": "@openzeppelin/contracts-upgradeable/proxy/utils/Initializable.sol",
      "solcConfig": {
        "version": "0.8.16",
        "settings": {
          "optimizer": {
            "enabled": false,
            "runs": 200
          },
          "outputSelection": {
            "*": {
              "*": [
                "abi",
                "evm.bytecode",
                "evm.deployedBytecode",
                "evm.methodIdentifiers",
                "metadata",
                "storageLayout"
              ],
              "": [
                "ast"
              ]
            }
          },
          "metadata": {
            "useLiteralContent": false
          }
        }
      },
      "imports": [
        "../../utils/AddressUpgradeable.sol"
      ],
      "versionPragmas": [
        "^0.8.2"
      ],
      "artifacts": [
        "Initializable"
      ]
    },
    "/home/swatimalode/Documents/Alloy/audit/smartcontract/node_modules/@openzeppelin/contracts-upgradeable/token/ERC20/extensions/IERC20MetadataUpgradeable.sol": {
      "lastModificationDate": 1684824407314,
      "contentHash": "9efcd5467a7f0bf533910ee8a267adb2",
      "sourceName": "@openzeppelin/contracts-upgradeable/token/ERC20/extensions/IERC20MetadataUpgradeable.sol",
      "solcConfig": {
        "version": "0.8.16",
        "settings": {
          "optimizer": {
            "enabled": false,
            "runs": 200
          },
          "outputSelection": {
            "*": {
              "*": [
                "abi",
                "evm.bytecode",
                "evm.deployedBytecode",
                "evm.methodIdentifiers",
                "metadata",
                "storageLayout"
              ],
              "": [
                "ast"
              ]
            }
          },
          "metadata": {
            "useLiteralContent": false
          }
        }
      },
      "imports": [
        "../IERC20Upgradeable.sol"
      ],
      "versionPragmas": [
        "^0.8.0"
      ],
      "artifacts": [
        "IERC20MetadataUpgradeable"
      ]
    },
    "/home/swatimalode/Documents/Alloy/audit/smartcontract/node_modules/@openzeppelin/contracts-upgradeable/utils/AddressUpgradeable.sol": {
      "lastModificationDate": 1684824406398,
      "contentHash": "228f256dbb21393bc9ad02648e222f74",
      "sourceName": "@openzeppelin/contracts-upgradeable/utils/AddressUpgradeable.sol",
      "solcConfig": {
        "version": "0.8.16",
        "settings": {
          "optimizer": {
            "enabled": false,
            "runs": 200
          },
          "outputSelection": {
            "*": {
              "*": [
                "abi",
                "evm.bytecode",
                "evm.deployedBytecode",
                "evm.methodIdentifiers",
                "metadata",
                "storageLayout"
              ],
              "": [
                "ast"
              ]
            }
          },
          "metadata": {
            "useLiteralContent": false
          }
        }
      },
      "imports": [],
      "versionPragmas": [
        "^0.8.1"
      ],
      "artifacts": [
        "AddressUpgradeable"
      ]
    },
    "/home/swatimalode/Documents/Alloy/audit/smartcontract/node_modules/@openzeppelin/contracts-upgradeable/security/ReentrancyGuardUpgradeable.sol": {
      "lastModificationDate": 1684824407686,
      "contentHash": "1453fc85149da6598faf08c46b88182d",
      "sourceName": "@openzeppelin/contracts-upgradeable/security/ReentrancyGuardUpgradeable.sol",
      "solcConfig": {
        "version": "0.8.16",
        "settings": {
          "optimizer": {
            "enabled": false,
            "runs": 200
          },
          "outputSelection": {
            "*": {
              "*": [
                "abi",
                "evm.bytecode",
                "evm.deployedBytecode",
                "evm.methodIdentifiers",
                "metadata",
                "storageLayout"
              ],
              "": [
                "ast"
              ]
            }
          },
          "metadata": {
            "useLiteralContent": false
          }
        }
      },
      "imports": [
        "../proxy/utils/Initializable.sol"
      ],
      "versionPragmas": [
        "^0.8.0"
      ],
      "artifacts": [
        "ReentrancyGuardUpgradeable"
      ]
    },
    "/home/swatimalode/Documents/Alloy/audit/smartcontract/node_modules/@openzeppelin/contracts-upgradeable/access/OwnableUpgradeable.sol": {
      "lastModificationDate": 1684824407662,
      "contentHash": "403ce8273abde646bff81558ddf512ad",
      "sourceName": "@openzeppelin/contracts-upgradeable/access/OwnableUpgradeable.sol",
      "solcConfig": {
        "version": "0.8.16",
        "settings": {
          "optimizer": {
            "enabled": false,
            "runs": 200
          },
          "outputSelection": {
            "*": {
              "*": [
                "abi",
                "evm.bytecode",
                "evm.deployedBytecode",
                "evm.methodIdentifiers",
                "metadata",
                "storageLayout"
              ],
              "": [
                "ast"
              ]
            }
          },
          "metadata": {
            "useLiteralContent": false
          }
        }
      },
      "imports": [
        "../utils/ContextUpgradeable.sol",
        "../proxy/utils/Initializable.sol"
      ],
      "versionPragmas": [
        "^0.8.0"
      ],
      "artifacts": [
        "OwnableUpgradeable"
      ]
    },
    "/home/swatimalode/Documents/Alloy/audit/smartcontract/node_modules/@openzeppelin/contracts-upgradeable/utils/cryptography/ECDSAUpgradeable.sol": {
      "lastModificationDate": 1684824406718,
      "contentHash": "b3e120a8002394aabbbc467369cd7390",
      "sourceName": "@openzeppelin/contracts-upgradeable/utils/cryptography/ECDSAUpgradeable.sol",
      "solcConfig": {
        "version": "0.8.16",
        "settings": {
          "optimizer": {
            "enabled": false,
            "runs": 200
          },
          "outputSelection": {
            "*": {
              "*": [
                "abi",
                "evm.bytecode",
                "evm.deployedBytecode",
                "evm.methodIdentifiers",
                "metadata",
                "storageLayout"
              ],
              "": [
                "ast"
              ]
            }
          },
          "metadata": {
            "useLiteralContent": false
          }
        }
      },
      "imports": [
        "../StringsUpgradeable.sol"
      ],
      "versionPragmas": [
        "^0.8.0"
      ],
      "artifacts": [
        "ECDSAUpgradeable"
      ]
    },
    "/home/swatimalode/Documents/Alloy/audit/smartcontract/node_modules/@openzeppelin/contracts-upgradeable/utils/cryptography/SignatureCheckerUpgradeable.sol": {
      "lastModificationDate": 1684824407722,
      "contentHash": "547b2c80da8dccb38b2bc88a75ba14ff",
      "sourceName": "@openzeppelin/contracts-upgradeable/utils/cryptography/SignatureCheckerUpgradeable.sol",
      "solcConfig": {
        "version": "0.8.16",
        "settings": {
          "optimizer": {
            "enabled": false,
            "runs": 200
          },
          "outputSelection": {
            "*": {
              "*": [
                "abi",
                "evm.bytecode",
                "evm.deployedBytecode",
                "evm.methodIdentifiers",
                "metadata",
                "storageLayout"
              ],
              "": [
                "ast"
              ]
            }
          },
          "metadata": {
            "useLiteralContent": false
          }
        }
      },
      "imports": [
        "./ECDSAUpgradeable.sol",
        "../AddressUpgradeable.sol",
        "../../interfaces/IERC1271Upgradeable.sol"
      ],
      "versionPragmas": [
        "^0.8.0"
      ],
      "artifacts": [
        "SignatureCheckerUpgradeable"
      ]
    },
    "/home/swatimalode/Documents/Alloy/audit/smartcontract/node_modules/@openzeppelin/contracts-upgradeable/utils/StringsUpgradeable.sol": {
      "lastModificationDate": 1684824407738,
      "contentHash": "3805d0267faeda96624b50a67ca89f08",
      "sourceName": "@openzeppelin/contracts-upgradeable/utils/StringsUpgradeable.sol",
      "solcConfig": {
        "version": "0.8.16",
        "settings": {
          "optimizer": {
            "enabled": false,
            "runs": 200
          },
          "outputSelection": {
            "*": {
              "*": [
                "abi",
                "evm.bytecode",
                "evm.deployedBytecode",
                "evm.methodIdentifiers",
                "metadata",
                "storageLayout"
              ],
              "": [
                "ast"
              ]
            }
          },
          "metadata": {
            "useLiteralContent": false
          }
        }
      },
      "imports": [
        "./math/MathUpgradeable.sol"
      ],
      "versionPragmas": [
        "^0.8.0"
      ],
      "artifacts": [
        "StringsUpgradeable"
      ]
    },
    "/home/swatimalode/Documents/Alloy/audit/smartcontract/node_modules/@openzeppelin/contracts-upgradeable/utils/math/MathUpgradeable.sol": {
      "lastModificationDate": 1684824407618,
      "contentHash": "469f71655418cc5f328fcc9bfdf10e9a",
      "sourceName": "@openzeppelin/contracts-upgradeable/utils/math/MathUpgradeable.sol",
      "solcConfig": {
        "version": "0.8.16",
        "settings": {
          "optimizer": {
            "enabled": false,
            "runs": 200
          },
          "outputSelection": {
            "*": {
              "*": [
                "abi",
                "evm.bytecode",
                "evm.deployedBytecode",
                "evm.methodIdentifiers",
                "metadata",
                "storageLayout"
              ],
              "": [
                "ast"
              ]
            }
          },
          "metadata": {
            "useLiteralContent": false
          }
        }
      },
      "imports": [],
      "versionPragmas": [
        "^0.8.0"
      ],
      "artifacts": [
        "MathUpgradeable"
      ]
    },
    "/home/swatimalode/Documents/Alloy/audit/smartcontract/node_modules/@openzeppelin/contracts-upgradeable/interfaces/IERC1271Upgradeable.sol": {
      "lastModificationDate": 1684824407274,
      "contentHash": "7e169522c39a2d02d418dc22a9f1aa1e",
      "sourceName": "@openzeppelin/contracts-upgradeable/interfaces/IERC1271Upgradeable.sol",
      "solcConfig": {
        "version": "0.8.16",
        "settings": {
          "optimizer": {
            "enabled": false,
            "runs": 200
          },
          "outputSelection": {
            "*": {
              "*": [
                "abi",
                "evm.bytecode",
                "evm.deployedBytecode",
                "evm.methodIdentifiers",
                "metadata",
                "storageLayout"
              ],
              "": [
                "ast"
              ]
            }
          },
          "metadata": {
            "useLiteralContent": false
          }
        }
      },
      "imports": [],
      "versionPragmas": [
        "^0.8.0"
      ],
      "artifacts": [
        "IERC1271Upgradeable"
      ]
    },
    "/home/swatimalode/Documents/Alloy/audit/smartcontract/node_modules/@openzeppelin/contracts-upgradeable/token/ERC721/ERC721Upgradeable.sol": {
      "lastModificationDate": 1684824407094,
      "contentHash": "1b383477952ce41c0f408a91680d6d18",
      "sourceName": "@openzeppelin/contracts-upgradeable/token/ERC721/ERC721Upgradeable.sol",
      "solcConfig": {
        "version": "0.8.16",
        "settings": {
          "optimizer": {
            "enabled": false,
            "runs": 200
          },
          "outputSelection": {
            "*": {
              "*": [
                "abi",
                "evm.bytecode",
                "evm.deployedBytecode",
                "evm.methodIdentifiers",
                "metadata",
                "storageLayout"
              ],
              "": [
                "ast"
              ]
            }
          },
          "metadata": {
            "useLiteralContent": false
          }
        }
      },
      "imports": [
        "./IERC721Upgradeable.sol",
        "./IERC721ReceiverUpgradeable.sol",
        "./extensions/IERC721MetadataUpgradeable.sol",
        "../../utils/AddressUpgradeable.sol",
        "../../utils/ContextUpgradeable.sol",
        "../../utils/StringsUpgradeable.sol",
        "../../utils/introspection/ERC165Upgradeable.sol",
        "../../proxy/utils/Initializable.sol"
      ],
      "versionPragmas": [
        "^0.8.0"
      ],
      "artifacts": [
        "ERC721Upgradeable"
      ]
    },
    "/home/swatimalode/Documents/Alloy/audit/smartcontract/node_modules/@openzeppelin/contracts-upgradeable/token/ERC721/IERC721Upgradeable.sol": {
      "lastModificationDate": 1684824407478,
      "contentHash": "407d093831013935f7b2ab603ef3f21c",
      "sourceName": "@openzeppelin/contracts-upgradeable/token/ERC721/IERC721Upgradeable.sol",
      "solcConfig": {
        "version": "0.8.16",
        "settings": {
          "optimizer": {
            "enabled": false,
            "runs": 200
          },
          "outputSelection": {
            "*": {
              "*": [
                "abi",
                "evm.bytecode",
                "evm.deployedBytecode",
                "evm.methodIdentifiers",
                "metadata",
                "storageLayout"
              ],
              "": [
                "ast"
              ]
            }
          },
          "metadata": {
            "useLiteralContent": false
          }
        }
      },
      "imports": [
        "../../utils/introspection/IERC165Upgradeable.sol"
      ],
      "versionPragmas": [
        "^0.8.0"
      ],
      "artifacts": [
        "IERC721Upgradeable"
      ]
    },
    "/home/swatimalode/Documents/Alloy/audit/smartcontract/node_modules/@openzeppelin/contracts-upgradeable/token/ERC721/IERC721ReceiverUpgradeable.sol": {
      "lastModificationDate": 1684824407458,
      "contentHash": "ba28cf60b52b00d2b3a190bcdf0952bd",
      "sourceName": "@openzeppelin/contracts-upgradeable/token/ERC721/IERC721ReceiverUpgradeable.sol",
      "solcConfig": {
        "version": "0.8.16",
        "settings": {
          "optimizer": {
            "enabled": false,
            "runs": 200
          },
          "outputSelection": {
            "*": {
              "*": [
                "abi",
                "evm.bytecode",
                "evm.deployedBytecode",
                "evm.methodIdentifiers",
                "metadata",
                "storageLayout"
              ],
              "": [
                "ast"
              ]
            }
          },
          "metadata": {
            "useLiteralContent": false
          }
        }
      },
      "imports": [],
      "versionPragmas": [
        "^0.8.0"
      ],
      "artifacts": [
        "IERC721ReceiverUpgradeable"
      ]
    },
    "/home/swatimalode/Documents/Alloy/audit/smartcontract/node_modules/@openzeppelin/contracts-upgradeable/utils/introspection/ERC165Upgradeable.sol": {
      "lastModificationDate": 1684824406838,
      "contentHash": "5f2d8b81c0ff5bd2047b4846c20b998d",
      "sourceName": "@openzeppelin/contracts-upgradeable/utils/introspection/ERC165Upgradeable.sol",
      "solcConfig": {
        "version": "0.8.16",
        "settings": {
          "optimizer": {
            "enabled": false,
            "runs": 200
          },
          "outputSelection": {
            "*": {
              "*": [
                "abi",
                "evm.bytecode",
                "evm.deployedBytecode",
                "evm.methodIdentifiers",
                "metadata",
                "storageLayout"
              ],
              "": [
                "ast"
              ]
            }
          },
          "metadata": {
            "useLiteralContent": false
          }
        }
      },
      "imports": [
        "./IERC165Upgradeable.sol",
        "../../proxy/utils/Initializable.sol"
      ],
      "versionPragmas": [
        "^0.8.0"
      ],
      "artifacts": [
        "ERC165Upgradeable"
      ]
    },
    "/home/swatimalode/Documents/Alloy/audit/smartcontract/node_modules/@openzeppelin/contracts-upgradeable/token/ERC721/extensions/IERC721MetadataUpgradeable.sol": {
      "lastModificationDate": 1684824407434,
      "contentHash": "76212ca0265501d1eb3dd1175e6afca4",
      "sourceName": "@openzeppelin/contracts-upgradeable/token/ERC721/extensions/IERC721MetadataUpgradeable.sol",
      "solcConfig": {
        "version": "0.8.16",
        "settings": {
          "optimizer": {
            "enabled": false,
            "runs": 200
          },
          "outputSelection": {
            "*": {
              "*": [
                "abi",
                "evm.bytecode",
                "evm.deployedBytecode",
                "evm.methodIdentifiers",
                "metadata",
                "storageLayout"
              ],
              "": [
                "ast"
              ]
            }
          },
          "metadata": {
            "useLiteralContent": false
          }
        }
      },
      "imports": [
        "../IERC721Upgradeable.sol"
      ],
      "versionPragmas": [
        "^0.8.0"
      ],
      "artifacts": [
        "IERC721MetadataUpgradeable"
      ]
    },
    "/home/swatimalode/Documents/Alloy/audit/smartcontract/node_modules/@openzeppelin/contracts-upgradeable/utils/introspection/IERC165Upgradeable.sol": {
      "lastModificationDate": 1684824407286,
      "contentHash": "d6ecf203a5e72c845be9bbf2f304a289",
      "sourceName": "@openzeppelin/contracts-upgradeable/utils/introspection/IERC165Upgradeable.sol",
      "solcConfig": {
        "version": "0.8.16",
        "settings": {
          "optimizer": {
            "enabled": false,
            "runs": 200
          },
          "outputSelection": {
            "*": {
              "*": [
                "abi",
                "evm.bytecode",
                "evm.deployedBytecode",
                "evm.methodIdentifiers",
                "metadata",
                "storageLayout"
              ],
              "": [
                "ast"
              ]
            }
          },
          "metadata": {
            "useLiteralContent": false
          }
        }
      },
      "imports": [],
      "versionPragmas": [
        "^0.8.0"
      ],
      "artifacts": [
        "IERC165Upgradeable"
      ]
    },
    "/home/swatimalode/Documents/Alloy/audit/smartcontract/contracts/ARC/IERC20Upgradeable.sol": {
      "lastModificationDate": 1684837111667,
      "contentHash": "c215d8e8ade82adc841297766c8efa6d",
      "sourceName": "contracts/ARC/IERC20Upgradeable.sol",
      "solcConfig": {
        "version": "0.8.16",
        "settings": {
          "optimizer": {
            "enabled": false,
            "runs": 200
          },
          "outputSelection": {
            "*": {
              "*": [
                "abi",
                "evm.bytecode",
                "evm.deployedBytecode",
                "evm.methodIdentifiers",
                "metadata",
                "storageLayout"
              ],
              "": [
                "ast"
              ]
            }
          },
          "metadata": {
            "useLiteralContent": false
          }
        }
      },
      "imports": [],
      "versionPragmas": [
        "^0.8.0"
      ],
      "artifacts": [
        "IERC20Upgradeable"
      ]
    },
    "/home/swatimalode/Documents/Alloy/audit/smartcontract/contracts/ARC/ArfInterface.sol": {
      "lastModificationDate": 1684836018584,
      "contentHash": "685b5b99d4f2976422b4cf5b4a344bb4",
      "sourceName": "contracts/ARC/ArfInterface.sol",
      "solcConfig": {
        "version": "0.8.16",
        "settings": {
          "optimizer": {
            "enabled": false,
            "runs": 200
          },
          "outputSelection": {
            "*": {
              "*": [
                "abi",
                "evm.bytecode",
                "evm.deployedBytecode",
                "evm.methodIdentifiers",
                "metadata",
                "storageLayout"
              ],
              "": [
                "ast"
              ]
            }
          },
          "metadata": {
            "useLiteralContent": false
          }
        }
      },
      "imports": [
        "@openzeppelin/contracts-upgradeable/token/ERC721/IERC721Upgradeable.sol"
      ],
      "versionPragmas": [
        "0.8.16"
      ],
      "artifacts": [
        "ARFInterface"
      ]
    },
    "/home/swatimalode/Documents/Alloy/audit/smartcontract/contracts/NIOZ/NiozERC20V2.sol": {
      "lastModificationDate": 1684921359685,
      "contentHash": "ac55f60a48e6bfd597438485816294ae",
      "sourceName": "contracts/NIOZ/NiozERC20V2.sol",
      "solcConfig": {
        "version": "0.8.16",
        "settings": {
          "optimizer": {
            "enabled": false,
            "runs": 200
          },
          "outputSelection": {
            "*": {
              "*": [
                "abi",
                "evm.bytecode",
                "evm.deployedBytecode",
                "evm.methodIdentifiers",
                "metadata",
                "storageLayout"
              ],
              "": [
                "ast"
              ]
            }
          },
          "metadata": {
            "useLiteralContent": false
          }
        }
      },
      "imports": [
        "./ERC20Upgradeable.sol",
        "./IERC721Upgradeable.sol",
        "@openzeppelin/contracts-upgradeable/access/OwnableUpgradeable.sol",
        "@openzeppelin/contracts-upgradeable/security/ReentrancyGuardUpgradeable.sol",
        "@openzeppelin/contracts-upgradeable/utils/cryptography/SignatureCheckerUpgradeable.sol",
        "@openzeppelin/contracts-upgradeable/utils/cryptography/ECDSAUpgradeable.sol"
      ],
      "versionPragmas": [
        "0.8.16"
      ],
      "artifacts": [
        "NiozERC20V2"
      ]
    },
    "/home/swatimalode/Documents/Alloy/audit/smartcontract/contracts/NIOZ/ERC20Upgradeable.sol": {
      "lastModificationDate": 1684835988134,
      "contentHash": "03a17f9c5cac1e3b455f0102e07353ab",
      "sourceName": "contracts/NIOZ/ERC20Upgradeable.sol",
      "solcConfig": {
        "version": "0.8.16",
        "settings": {
          "optimizer": {
            "enabled": false,
            "runs": 200
          },
          "outputSelection": {
            "*": {
              "*": [
                "abi",
                "evm.bytecode",
                "evm.deployedBytecode",
                "evm.methodIdentifiers",
                "metadata",
                "storageLayout"
              ],
              "": [
                "ast"
              ]
            }
          },
          "metadata": {
            "useLiteralContent": false
          }
        }
      },
      "imports": [
        "@openzeppelin/contracts-upgradeable/token/ERC20/IERC20Upgradeable.sol",
        "@openzeppelin/contracts-upgradeable/token/ERC20/extensions/IERC20MetadataUpgradeable.sol",
        "@openzeppelin/contracts-upgradeable/utils/ContextUpgradeable.sol",
        "@openzeppelin/contracts-upgradeable/proxy/utils/Initializable.sol"
      ],
      "versionPragmas": [
        "^0.8.0"
      ],
      "artifacts": [
        "ERC20Upgradeable"
      ]
    },
    "/home/swatimalode/Documents/Alloy/audit/smartcontract/contracts/NIOZ/IERC721Upgradeable.sol": {
      "lastModificationDate": 1684835988134,
      "contentHash": "4926622c102e50b9fcb013b25995a586",
      "sourceName": "contracts/NIOZ/IERC721Upgradeable.sol",
      "solcConfig": {
        "version": "0.8.16",
        "settings": {
          "optimizer": {
            "enabled": false,
            "runs": 200
          },
          "outputSelection": {
            "*": {
              "*": [
                "abi",
                "evm.bytecode",
                "evm.deployedBytecode",
                "evm.methodIdentifiers",
                "metadata",
                "storageLayout"
              ],
              "": [
                "ast"
              ]
            }
          },
          "metadata": {
            "useLiteralContent": false
          }
        }
      },
      "imports": [],
      "versionPragmas": [
        "^0.8.0"
      ],
      "artifacts": [
        "IERC721Upgradeable"
      ]
    },
    "/home/swatimalode/Documents/Alloy/audit/smartcontract/contracts/ARF/ArfERC721V2.sol": {
      "lastModificationDate": 1685033681998,
      "contentHash": "65aba5ea5df83b05ac67e968f46fd3ed",
      "sourceName": "contracts/ARF/ArfERC721V2.sol",
      "solcConfig": {
        "version": "0.8.16",
        "settings": {
          "optimizer": {
            "enabled": false,
            "runs": 200
          },
          "outputSelection": {
            "*": {
              "*": [
                "abi",
                "evm.bytecode",
                "evm.deployedBytecode",
                "evm.methodIdentifiers",
                "metadata",
                "storageLayout"
              ],
              "": [
                "ast"
              ]
            }
          },
          "metadata": {
            "useLiteralContent": false
          }
        }
      },
      "imports": [
        "@openzeppelin/contracts-upgradeable/token/ERC721/ERC721Upgradeable.sol",
        "@openzeppelin/contracts-upgradeable/access/OwnableUpgradeable.sol",
        "@openzeppelin/contracts-upgradeable/utils/StringsUpgradeable.sol",
        "@openzeppelin/contracts-upgradeable/security/ReentrancyGuardUpgradeable.sol",
        "@openzeppelin/contracts-upgradeable/utils/cryptography/SignatureCheckerUpgradeable.sol",
        "./IERC20Upgradeable.sol",
        "./MintpegInterface.sol"
      ],
      "versionPragmas": [
        "0.8.16"
      ],
      "artifacts": [
        "ArfERC721V2"
      ]
    },
    "/home/swatimalode/Documents/Alloy/audit/smartcontract/contracts/ARF/IERC20Upgradeable.sol": {
      "lastModificationDate": 1684837212226,
      "contentHash": "949c1ac12ba71fd9a73fb2e1fce987ec",
      "sourceName": "contracts/ARF/IERC20Upgradeable.sol",
      "solcConfig": {
        "version": "0.8.16",
        "settings": {
          "optimizer": {
            "enabled": false,
            "runs": 200
          },
          "outputSelection": {
            "*": {
              "*": [
                "abi",
                "evm.bytecode",
                "evm.deployedBytecode",
                "evm.methodIdentifiers",
                "metadata",
                "storageLayout"
              ],
              "": [
                "ast"
              ]
            }
          },
          "metadata": {
            "useLiteralContent": false
          }
        }
      },
      "imports": [],
      "versionPragmas": [
        "^0.8.0"
      ],
      "artifacts": [
        "IERC20Upgradeable"
      ]
    },
    "/home/swatimalode/Documents/Alloy/audit/smartcontract/contracts/ARF/MintpegInterface.sol": {
      "lastModificationDate": 1684837409259,
      "contentHash": "10772bc87e632fc0344fd5cb2bfa5bdb",
      "sourceName": "contracts/ARF/MintpegInterface.sol",
      "solcConfig": {
        "version": "0.8.16",
        "settings": {
          "optimizer": {
            "enabled": false,
            "runs": 200
          },
          "outputSelection": {
            "*": {
              "*": [
                "abi",
                "evm.bytecode",
                "evm.deployedBytecode",
                "evm.methodIdentifiers",
                "metadata",
                "storageLayout"
              ],
              "": [
                "ast"
              ]
            }
          },
          "metadata": {
            "useLiteralContent": false
          }
        }
      },
      "imports": [],
      "versionPragmas": [
        "^0.8.16"
      ],
      "artifacts": [
        "Mintpeg"
      ]
    },
    "/home/swatimalode/Documents/Alloy/audit/smartcontract/contracts/ARC/AlloyERC721V2.sol": {
      "lastModificationDate": 1684840560176,
      "contentHash": "5caef4a83b733371dab099e94e02f75d",
      "sourceName": "contracts/ARC/AlloyERC721V2.sol",
      "solcConfig": {
        "version": "0.8.16",
        "settings": {
          "optimizer": {
            "enabled": false,
            "runs": 200
          },
          "outputSelection": {
            "*": {
              "*": [
                "abi",
                "evm.bytecode",
                "evm.deployedBytecode",
                "evm.methodIdentifiers",
                "metadata",
                "storageLayout"
              ],
              "": [
                "ast"
              ]
            }
          },
          "metadata": {
            "useLiteralContent": false
          }
        }
      },
      "imports": [
        "@openzeppelin/contracts-upgradeable/token/ERC721/ERC721Upgradeable.sol",
        "@openzeppelin/contracts-upgradeable/access/OwnableUpgradeable.sol",
        "@openzeppelin/contracts-upgradeable/utils/StringsUpgradeable.sol",
        "@openzeppelin/contracts-upgradeable/security/ReentrancyGuardUpgradeable.sol",
        "@openzeppelin/contracts-upgradeable/utils/cryptography/SignatureCheckerUpgradeable.sol",
        "./IERC20Upgradeable.sol",
        "./ArfInterface.sol"
      ],
      "versionPragmas": [
        "0.8.16"
      ],
      "artifacts": [
        "AlloyERC721V2"
      ]
    },
    "/home/swatimalode/Documents/Alloy/audit/smartcontract/contracts/CONSTRUCT/ConstructERC721V1.sol": {
      "lastModificationDate": 1684840690938,
      "contentHash": "7e2bc29f6f027f6777efefac1735c82b",
      "sourceName": "contracts/CONSTRUCT/ConstructERC721V1.sol",
      "solcConfig": {
        "version": "0.8.16",
        "settings": {
          "optimizer": {
            "enabled": false,
            "runs": 200
          },
          "outputSelection": {
            "*": {
              "*": [
                "abi",
                "evm.bytecode",
                "evm.deployedBytecode",
                "evm.methodIdentifiers",
                "metadata",
                "storageLayout"
              ],
              "": [
                "ast"
              ]
            }
          },
          "metadata": {
            "useLiteralContent": false
          }
        }
      },
      "imports": [
        "@openzeppelin/contracts-upgradeable/token/ERC721/ERC721Upgradeable.sol",
        "@openzeppelin/contracts-upgradeable/access/OwnableUpgradeable.sol",
        "@openzeppelin/contracts-upgradeable/utils/StringsUpgradeable.sol",
        "@openzeppelin/contracts-upgradeable/security/ReentrancyGuardUpgradeable.sol",
        "@openzeppelin/contracts-upgradeable/utils/cryptography/SignatureCheckerUpgradeable.sol",
        "./IERC20Upgradeable.sol",
        "./MintpegInterface.sol"
      ],
      "versionPragmas": [
        "0.8.16"
      ],
      "artifacts": [
        "ConstructERC721V1"
      ]
    },
    "/home/swatimalode/Documents/Alloy/audit/smartcontract/contracts/CONSTRUCT/MintpegInterface.sol": {
      "lastModificationDate": 1684837749711,
      "contentHash": "fbdedbbb7c494476042e498b202336fc",
      "sourceName": "contracts/CONSTRUCT/MintpegInterface.sol",
      "solcConfig": {
        "version": "0.8.16",
        "settings": {
          "optimizer": {
            "enabled": false,
            "runs": 200
          },
          "outputSelection": {
            "*": {
              "*": [
                "abi",
                "evm.bytecode",
                "evm.deployedBytecode",
                "evm.methodIdentifiers",
                "metadata",
                "storageLayout"
              ],
              "": [
                "ast"
              ]
            }
          },
          "metadata": {
            "useLiteralContent": false
          }
        }
      },
      "imports": [],
      "versionPragmas": [
        "^0.8.16"
      ],
      "artifacts": [
        "Mintpeg"
      ]
    },
    "/home/swatimalode/Documents/Alloy/audit/smartcontract/contracts/CONSTRUCT/IERC20Upgradeable.sol": {
      "lastModificationDate": 1684837749707,
      "contentHash": "949c1ac12ba71fd9a73fb2e1fce987ec",
      "sourceName": "contracts/CONSTRUCT/IERC20Upgradeable.sol",
      "solcConfig": {
        "version": "0.8.16",
        "settings": {
          "optimizer": {
            "enabled": false,
            "runs": 200
          },
          "outputSelection": {
            "*": {
              "*": [
                "abi",
                "evm.bytecode",
                "evm.deployedBytecode",
                "evm.methodIdentifiers",
                "metadata",
                "storageLayout"
              ],
              "": [
                "ast"
              ]
            }
          },
          "metadata": {
            "useLiteralContent": false
          }
        }
      },
      "imports": [],
      "versionPragmas": [
        "^0.8.0"
      ],
      "artifacts": [
        "IERC20Upgradeable"
      ]
    },
    "/home/swatimalode/Documents/Alloy/audit/smartcontract/contracts/ARC/AlloyERC721V1.sol": {
      "lastModificationDate": 1684922617930,
      "contentHash": "0a0e1bccadf68f9cfab1db9f5477d3e8",
      "sourceName": "contracts/ARC/AlloyERC721V1.sol",
      "solcConfig": {
        "version": "0.8.16",
        "settings": {
          "optimizer": {
            "enabled": false,
            "runs": 200
          },
          "outputSelection": {
            "*": {
              "*": [
                "abi",
                "evm.bytecode",
                "evm.deployedBytecode",
                "evm.methodIdentifiers",
                "metadata",
                "storageLayout"
              ],
              "": [
                "ast"
              ]
            }
          },
          "metadata": {
            "useLiteralContent": false
          }
        }
      },
      "imports": [
        "@openzeppelin/contracts-upgradeable/token/ERC721/ERC721Upgradeable.sol",
        "@openzeppelin/contracts-upgradeable/access/OwnableUpgradeable.sol",
        "@openzeppelin/contracts-upgradeable/utils/StringsUpgradeable.sol",
        "@openzeppelin/contracts-upgradeable/security/ReentrancyGuardUpgradeable.sol",
        "@openzeppelin/contracts-upgradeable/utils/cryptography/SignatureCheckerUpgradeable.sol",
        "./IERC20Upgradeable.sol",
        "./ArfInterface.sol"
      ],
      "versionPragmas": [
        "0.8.16"
      ],
      "artifacts": [
        "AlloyERC721V1"
      ]
    },
    "/home/swatimalode/Documents/Alloy/audit/smartcontract/contracts/NIOZ/NiozERC20V1.sol": {
      "lastModificationDate": 1684922619022,
      "contentHash": "9b54e592d0abbd8c805fc5c8156fb517",
      "sourceName": "contracts/NIOZ/NiozERC20V1.sol",
      "solcConfig": {
        "version": "0.8.16",
        "settings": {
          "optimizer": {
            "enabled": false,
            "runs": 200
          },
          "outputSelection": {
            "*": {
              "*": [
                "abi",
                "evm.bytecode",
                "evm.deployedBytecode",
                "evm.methodIdentifiers",
                "metadata",
                "storageLayout"
              ],
              "": [
                "ast"
              ]
            }
          },
          "metadata": {
            "useLiteralContent": false
          }
        }
      },
      "imports": [
        "./ERC20Upgradeable.sol",
        "./IERC721Upgradeable.sol",
        "@openzeppelin/contracts-upgradeable/access/OwnableUpgradeable.sol",
        "@openzeppelin/contracts-upgradeable/security/ReentrancyGuardUpgradeable.sol",
        "@openzeppelin/contracts-upgradeable/utils/cryptography/SignatureCheckerUpgradeable.sol"
      ],
      "versionPragmas": [
        "0.8.16"
      ],
      "artifacts": [
        "NiozERC20V1"
      ]
    },
    "/home/swatimalode/Documents/Alloy/audit/smartcontract/contracts/ARF/ArfERC721V1.sol": {
      "lastModificationDate": 1684925460877,
      "contentHash": "6b85d407efa12cf4c243041fae42f45d",
      "sourceName": "contracts/ARF/ArfERC721V1.sol",
      "solcConfig": {
        "version": "0.8.16",
        "settings": {
          "optimizer": {
            "enabled": false,
            "runs": 200
          },
          "outputSelection": {
            "*": {
              "*": [
                "abi",
                "evm.bytecode",
                "evm.deployedBytecode",
                "evm.methodIdentifiers",
                "metadata",
                "storageLayout"
              ],
              "": [
                "ast"
              ]
            }
          },
          "metadata": {
            "useLiteralContent": false
          }
        }
      },
      "imports": [
        "@openzeppelin/contracts-upgradeable/token/ERC721/ERC721Upgradeable.sol",
        "@openzeppelin/contracts-upgradeable/access/OwnableUpgradeable.sol",
        "@openzeppelin/contracts-upgradeable/utils/StringsUpgradeable.sol",
        "@openzeppelin/contracts-upgradeable/security/ReentrancyGuardUpgradeable.sol",
        "@openzeppelin/contracts-upgradeable/utils/cryptography/SignatureCheckerUpgradeable.sol",
        "./IERC20Upgradeable.sol",
        "./MintpegInterface.sol"
      ],
      "versionPragmas": [
        "0.8.16"
      ],
      "artifacts": [
        "ArfERC721V1"
      ]
    },
    "/home/swatimalode/Documents/Alloy/audit/smartcontract/contracts/EXTRACONSTRACTS/Joepegs.sol": {
      "lastModificationDate": 1684932068863,
      "contentHash": "3e623f84a198bd44a95c3de9d4dcbef9",
      "sourceName": "contracts/EXTRACONSTRACTS/Joepegs.sol",
      "solcConfig": {
        "version": "0.8.16",
        "settings": {
          "optimizer": {
            "enabled": false,
            "runs": 200
          },
          "outputSelection": {
            "*": {
              "*": [
                "abi",
                "evm.bytecode",
                "evm.deployedBytecode",
                "evm.methodIdentifiers",
                "metadata",
                "storageLayout"
              ],
              "": [
                "ast"
              ]
            }
          },
          "metadata": {
            "useLiteralContent": false
          }
        }
      },
      "imports": [
        "@openzeppelin/contracts-upgradeable/token/ERC721/ERC721Upgradeable.sol",
        "@openzeppelin/contracts-upgradeable/access/OwnableUpgradeable.sol"
      ],
      "versionPragmas": [
        "0.8.16"
      ],
      "artifacts": [
        "Joepegs"
      ]
    }
  }
}
